logcatter/__init__.py
logcatter/color.py
logcatter/command.py
logcatter/formatter.py
logcatter/level.py
logcatter/log.py
logcatter/logcat.py
logcatter-0.3.3.dist-info/METADATA
logcatter-0.3.3.dist-info/WHEEL
logcatter-0.3.3.dist-info/licenses/LICENSE
logcatter-0.3.3.dist-info/RECORD
