Metadata-Version: 2.4
Name: logcatter
Version: 0.3.3
Summary: Logcat style log library
Project-URL: Homepage, https://github.com/RivMt/logcatter
Project-URL: Issues, https://github.com/RivMt/logcatter/issues
Author-email: KANG SAN <san.kang@rivmt.com>
License-Expression: MIT
License-File: LICENSE
Classifier: Operating System :: OS Independent
Classifier: Programming Language :: Python :: 3
Requires-Python: >=3.7
